django_functest/__init__.py
django_functest/base.py
django_functest/exceptions.py
django_functest/files.py
django_functest/funcselenium.py
django_functest/funcwebtest.py
django_functest/models.py
django_functest/server.py
django_functest/urls.py
django_functest/utils.py
django_functest/templates/django_functest/base.html
django_functest-1.6.2.dist-info/licenses/AUTHORS.rst
django_functest-1.6.2.dist-info/licenses/LICENSE
django_functest-1.6.2.dist-info/METADATA
django_functest-1.6.2.dist-info/WHEEL
django_functest-1.6.2.dist-info/top_level.txt
django_functest-1.6.2.dist-info/RECORD
