Metadata-Version: 2.4
Name: django-functest
Version: 1.6.2
Summary: Helpers for creating functional tests in Django, with a unified API for WebTest and Selenium tests.
Author-email: Luke Plant <luke@lukeplant.me.uk>
License: BSD
Project-URL: Homepage, https://github.com/django-functest/django-functest
Keywords: django-functest
Classifier: Development Status :: 5 - Production/Stable
Classifier: Framework :: Django
Classifier: Framework :: Django :: 2.2
Classifier: Framework :: Django :: 3.0
Classifier: Framework :: Django :: 3.1
Classifier: Framework :: Django :: 3.2
Classifier: Framework :: Django :: 4.0
Classifier: Framework :: Django :: 4.1
Classifier: Framework :: Django :: 4.2
Classifier: Framework :: Django :: 5.0
Classifier: Framework :: Django :: 5.2
Classifier: Intended Audience :: Developers
Classifier: License :: OSI Approved :: BSD License
Classifier: Natural Language :: English
Classifier: Programming Language :: Python :: 3
Classifier: Programming Language :: Python :: 3.8
Classifier: Programming Language :: Python :: 3.9
Classifier: Programming Language :: Python :: 3.10
Classifier: Programming Language :: Python :: 3.11
Classifier: Programming Language :: Python :: 3.12
Classifier: Programming Language :: Python :: 3.13
Requires-Python: >=3.8
License-File: LICENSE
License-File: AUTHORS.rst
Requires-Dist: django-webtest>=1.9.11
Requires-Dist: WebTest>=3
Requires-Dist: selenium>=4
Requires-Dist: furl>=2
Requires-Dist: pyquery>=1.2.10
Requires-Dist: Django>=2.0
Dynamic: license-file
